FuxuanTracer/__init__.py
FuxuanTracer/__metadata__.py
FuxuanTracer/all.py
FuxuanTracer/core/__init__.py
FuxuanTracer/core/datapack.py
FuxuanTracer/core/scan.py
FuxuanTracer/dependecy/__init__.py
FuxuanTracer/dependecy/needModules.py
FuxuanTracer/utils/Device.py
FuxuanTracer/utils/Protocol.py
FuxuanTracer/utils/__init__.py
FuxuanTracer/utils/_firewall.py
FuxuanTracer/utils/_usePointer.py
FuxuanTracer/utils/dataPackCatcher.py
FuxuanTracer/utils/dataPakResult.py
FuxuanTracer/utils/excformat.py
FuxuanTracer/utils/helpers.py
FuxuanTracer/utils/httpsDecrypter.py
FuxuanTracer/utils/logger.py
FuxuanTracer-0.0.1.dist-info/LICENSE
FuxuanTracer-0.0.1.dist-info/METADATA
FuxuanTracer-0.0.1.dist-info/WHEEL
FuxuanTracer-0.0.1.dist-info/top_level.txt
FuxuanTracer-0.0.1.dist-info/RECORD
