Metadata-Version: 2.1
Name: FuxuanTracer
Version: 0.0.1
Summary: A useful logging library for Python
Home-page: https://www.github.com/KOKOMI12345/FuxuanTracer
Author: 符玄
Author-email: 3072252442@qq.com
License: MIT
Classifier: Programming Language :: Python :: 3
Classifier: License :: OSI Approved :: MIT License
Classifier: Operating System :: OS Independent
License-File: LICENSE
